CHANGES.txt
LICENSE.txt
MANIFEST.in
README.txt
hiverunner
setup.py
bin/hiverunner
hiverunner/__init__.py
hiverunner.egg-info/PKG-INFO
hiverunner.egg-info/SOURCES.txt
hiverunner.egg-info/dependency_links.txt
hiverunner.egg-info/requires.txt
hiverunner.egg-info/top_level.txt