Metadata-Version: 1.0
Name: hiverunner
Version: 1.0.1
Summary: Hive Runner is a python script that pulls saved queries from Beeswax, runs the queries on Hive, and stores the results in Memcache.
Home-page: https://github.com/bellycard/hiverunner
Author: Belly
Author-email: hiverunner@bellycard.com
License: Apache License 2.0
Platform: UNKNOWN
